ms_settings/__init__.py
ms_settings/patch.py
ms_settings-0.1.2.dist-info/LICENSE
ms_settings-0.1.2.dist-info/METADATA
ms_settings-0.1.2.dist-info/WHEEL
ms_settings-0.1.2.dist-info/top_level.txt
ms_settings-0.1.2.dist-info/RECORD
