Metadata-Version: 2.1
Name: ms-settings
Version: 0.1.2
Summary: A simple setting tool for project
Home-page: http://gitlab.com/liang.guisheng/py_settings
Author: Liang Guisheng
Author-email: theol.liang@gmail.com
License: MIT
Keywords: python settings configuration
Platform: UNKNOWN
Classifier: Programming Language :: Python :: 3
Classifier: Intended Audience :: Developers
Classifier: License :: OSI Approved :: MIT License
Classifier: Operating System :: OS Independent
Provides-Extra: dev
Requires-Dist: pytest-cov (==2.7.1) ; extra == 'dev'
Requires-Dist: safety (==1.9.0) ; extra == 'dev'
